Workbook

Sheet README
A1: PAYSPIN FINANCIAL MODEL v2 - VOLUME-DRIVEN, CORRECTED YAPILY PRICING
A3: Yapily: EUR 1,100/mo fixed (license 500 + data 300 + platform 300) incl. up to 3,000 tx/mo;
A4: EUR 0.30 per transaction above 3,000/mo. License + data stay fixed at any volume.
A5: Driven by founder transaction targets: ~100k tx (Y1), ~200k (Y2), ~350k (Y3, assumption).
A7: CONFIG A = your targets on the EUR 0.30 rail. Gross margin is NEGATIVE: the rail costs more
A8: than total revenue. Growing volume loses money faster. <-- the key warning.
A9: CONFIG B = the fix: Yapily renegotiated to EUR 0.10/tx at volume, business repriced to
A10: EUR 0.40/tx yield, free-consumer share capped at 40%, ROSCA moved to Phase-3 (near-zero) from M18.
A12: Edit the yellow Assumptions cells to flex rail rate, business yield, prices, Phase-3 rate.
A13: Money columns on the Config sheets are LIVE FORMULAS; tx volumes & mix are inputs.

Sheet Assumptions
A1: Assumption | B1: Value | C1: Note
A2: yapily_included | B2: 3000 | C2: Tx included in EUR 1,100/mo fixed bundle
A3: yapily_rate_A | B3: 0.3 | C3: Per-tx cost above bundle (current deal)
A4: yapily_rate_B | B4: 0.1 | C4: Renegotiated per-tx at volume (target)
A5: c_bill_price | B5: 0.5 | C5: EUR per billable consumer link
A6: biz_yield_A | B6: 0.22 | C6: Business revenue/tx, 'beat-Tikkie' pricing
A7: biz_yield_B | B7: 0.4 | C7: Business revenue/tx repriced (sub + per-tx)
A8: rosca_user_mo | B8: 1.5 | C8: ROSCA fee per user / month
A9: rosca_tx_per_user | B9: 1.1667 | C9: ROSCA tx per user / month (7 per 6-person circle)
A10: phase3_rosca_rate | B10: 0.02 | C10: Marginal cost/tx for ROSCA on Phase-3 rail

Sheet Config_A_targets
A1: Month | B1: Total tx | C1: tx Consumer-free | D1: tx Consumer-billable | E1: tx Business | F1: tx ROSCA | G1: ROSCA users | H1: Rev Consumer | I1: Rev Business | J1: Rev ROSCA | K1: TOTAL REVENUE | L1: Yapily | M1: Other opex | N1: Contingency 10% | O1: One-time | P1: TOTAL COST | Q1: EBT | R1: CUM CASH | S1: Gross margin %
A2: 1 | B2: 3233 | C2: 2005 | D2: 97 | E2: 744 | F2: 388 | G2: =F2/Assumptions!$B$9 | H2: =D2*Assumptions!$B$5 | I2: =E2*Assumptions!$B$6 | J2: =G2*Assumptions!$B$8 | K2: =H2+I2+J2 | L2: =1100+Assumptions!$B$3*MAX(0,B2-Assumptions!$B$2) | M2: 3200 | N2: =0.1*(L2+M2) | O2: 4200 | P2: =L2+M2+N2+O2 | Q2: =K2-P2 | R2: =Q2 | S2: =IF(K2=0,0,(K2-L2)/K2)
A3: 2 | B3: 3773 | C3: 2339 | D3: 113 | E3: 868 | F3: 453 | G3: =F3/Assumptions!$B$9 | H3: =D3*Assumptions!$B$5 | I3: =E3*Assumptions!$B$6 | J3: =G3*Assumptions!$B$8 | K3: =H3+I3+J3 | L3: =1100+Assumptions!$B$3*MAX(0,B3-Assumptions!$B$2) | M3: 3200 | N3: =0.1*(L3+M3) | O3: 0 | P3: =L3+M3+N3+O3 | Q3: =K3-P3 | R3: =R2+Q3 | S3: =IF(K3=0,0,(K3-L3)/K3)
A4: 3 | B4: 4397 | C4: 2726 | D4: 132 | E4: 1011 | F4: 528 | G4: =F4/Assumptions!$B$9 | H4: =D4*Assumptions!$B$5 | I4: =E4*Assumptions!$B$6 | J4: =G4*Assumptions!$B$8 | K4: =H4+I4+J4 | L4: =1100+Assumptions!$B$3*MAX(0,B4-Assumptions!$B$2) | M4: 3200 | N4: =0.1*(L4+M4) | O4: 0 | P4: =L4+M4+N4+O4 | Q4: =K4-P4 | R4: =R3+Q4 | S4: =IF(K4=0,0,(K4-L4)/K4)
A5: 4 | B5: 5120 | C5: 3174 | D5: 154 | E5: 1178 | F5: 614 | G5: =F5/Assumptions!$B$9 | H5: =D5*Assumptions!$B$5 | I5: =E5*Assumptions!$B$6 | J5: =G5*Assumptions!$B$8 | K5: =H5+I5+J5 | L5: =1100+Assumptions!$B$3*MAX(0,B5-Assumptions!$B$2) | M5: 6200 | N5: =0.1*(L5+M5) | O5: 0 | P5: =L5+M5+N5+O5 | Q5: =K5-P5 | R5: =R4+Q5 | S5: =IF(K5=0,0,(K5-L5)/K5)
A6: 5 | B6: 5953 | C6: 3691 | D6: 179 | E6: 1369 | F6: 714 | G6: =F6/Assumptions!$B$9 | H6: =D6*Assumptions!$B$5 | I6: =E6*Assumptions!$B$6 | J6: =G6*Assumptions!$B$8 | K6: =H6+I6+J6 | L6: =1100+Assumptions!$B$3*MAX(0,B6-Assumptions!$B$2) | M6: 6200 | N6: =0.1*(L6+M6) | O6: 0 | P6: =L6+M6+N6+O6 | Q6: =K6-P6 | R6: =R5+Q6 | S6: =IF(K6=0,0,(K6-L6)/K6)
A7: 6 | B7: 6912 | C7: 4285 | D7: 207 | E7: 1590 | F7: 829 | G7: =F7/Assumptions!$B$9 | H7: =D7*Assumptions!$B$5 | I7: =E7*Assumptions!$B$6 | J7: =G7*Assumptions!$B$8 | K7: =H7+I7+J7 | L7: =1100+Assumptions!$B$3*MAX(0,B7-Assumptions!$B$2) | M7: 6200 | N7: =0.1*(L7+M7) | O7: 0 | P7: =L7+M7+N7+O7 | Q7: =K7-P7 | R7: =R6+Q7 | S7: =IF(K7=0,0,(K7-L7)/K7)
A8: 7 | B8: 8011 | C8: 4967 | D8: 240 | E8: 1843 | F8: 961 | G8: =F8/Assumptions!$B$9 | H8: =D8*Assumptions!$B$5 | I8: =E8*Assumptions!$B$6 | J8: =G8*Assumptions!$B$8 | K8: =H8+I8+J8 | L8: =1100+Assumptions!$B$3*MAX(0,B8-Assumptions!$B$2) | M8: 13000 | N8: =0.1*(L8+M8) | O8: 1000 | P8: =L8+M8+N8+O8 | Q8: =K8-P8 | R8: =R7+Q8 | S8: =IF(K8=0,0,(K8-L8)/K8)
A9: 8 | B9: 9268 | C9: 5746 | D9: 278 | E9: 2132 | F9: 1112 | G9: =F9/Assumptions!$B$9 | H9: =D9*Assumptions!$B$5 | I9: =E9*Assumptions!$B$6 | J9: =G9*Assumptions!$B$8 | K9: =H9+I9+J9 | L9: =1100+Assumptions!$B$3*MAX(0,B9-Assumptions!$B$2) | M9: 13000 | N9: =0.1*(L9+M9) | O9: 0 | P9: =L9+M9+N9+O9 | Q9: =K9-P9 | R9: =R8+Q9 | S9: =IF(K9=0,0,(K9-L9)/K9)
A10: 9 | B10: 10697 | C10: 6632 | D10: 321 | E10: 2460 | F10: 1284 | G10: =F10/Assumptions!$B$9 | H10: =D10*Assumptions!$B$5 | I10: =E10*Assumptions!$B$6 | J10: =G10*Assumptions!$B$8 | K10: =H10+I10+J10 | L10: =1100+Assumptions!$B$3*MAX(0,B10-Assumptions!$B$2) | M10: 13000 | N10: =0.1*(L10+M10) | O10: 3000 | P10: =L10+M10+N10+O10 | Q10: =K10-P10 | R10: =R9+Q10 | S10: =IF(K10=0,0,(K10-L10)/K10)
A11: 10 | B11: 12316 | C11: 7636 | D11: 369 | E11: 2833 | F11: 1478 | G11: =F11/Assumptions!$B$9 | H11: =D11*Assumptions!$B$5 | I11: =E11*Assumptions!$B$6 | J11: =G11*Assumptions!$B$8 | K11: =H11+I11+J11 | L11: =1100+Assumptions!$B$3*MAX(0,B11-Assumptions!$B$2) | M11: 13000 | N11: =0.1*(L11+M11) | O11: 0 | P11: =L11+M11+N11+O11 | Q11: =K11-P11 | R11: =R10+Q11 | S11: =IF(K11=0,0,(K11-L11)/K11)
A12: 11 | B12: 14139 | C12: 8766 | D12: 424 | E12: 3252 | F12: 1697 | G12: =F12/Assumptions!$B$9 | H12: =D12*Assumptions!$B$5 | I12: =E12*Assumptions!$B$6 | J12: =G12*Assumptions!$B$8 | K12: =H12+I12+J12 | L12: =1100+Assumptions!$B$3*MAX(0,B12-Assumptions!$B$2) | M12: 13000 | N12: =0.1*(L12+M12) | O12: 0 | P12: =L12+M12+N12+O12 | Q12: =K12-P12 | R12: =R11+Q12 | S12: =IF(K12=0,0,(K12-L12)/K12)
A13: 12 | B13: 16180 | C13: 10032 | D13: 485 | E13: 3722 | F13: 1942 | G13: =F13/Assumptions!$B$9 | H13: =D13*Assumptions!$B$5 | I13: =E13*Assumptions!$B$6 | J13: =G13*Assumptions!$B$8 | K13: =H13+I13+J13 | L13: =1100+Assumptions!$B$3*MAX(0,B13-Assumptions!$B$2) | M13: 13000 | N13: =0.1*(L13+M13) | O13: 0 | P13: =L13+M13+N13+O13 | Q13: =K13-P13 | R13: =R12+Q13 | S13: =IF(K13=0,0,(K13-L13)/K13)
A14: 13 | B14: 8571 | C14: 4714 | D14: 300 | E14: 2400 | F14: 1157 | G14: =F14/Assumptions!$B$9 | H14: =D14*Assumptions!$B$5 | I14: =E14*Assumptions!$B$6 | J14: =G14*Assumptions!$B$8 | K14: =H14+I14+J14 | L14: =1100+Assumptions!$B$3*MAX(0,B14-Assumptions!$B$2) | M14: 25350 | N14: =0.1*(L14+M14) | O14: 0 | P14: =L14+M14+N14+O14 | Q14: =K14-P14 | R14: =R13+Q14 | S14: =IF(K14=0,0,(K14-L14)/K14)
... A37: 36 | B37: 33721 | C37: 16861 | D37: 1349 | E37: 10791 | F37: 4721 | G37: =F37/Assumptions!$B$9 | H37: =D37*Assumptions!$B$5 | I37: =E37*Assumptions!$B$6 | J37: =G37*Assumptions!$B$8 | K37: =H37+I37+J37 | L37: =1100+Assumptions!$B$3*MAX(0,B37-Assumptions!$B$2) | M37: 39250 | N37: =0.1*(L37+M37) | O37: 0 | P37: =L37+M37+N37+O37 | Q37: =K37-P37 | R37: =R36+Q37 | S37: =IF(K37=0,0,(K37-L37)/K37)

Sheet Config_B_viable
A1: Month | B1: Total tx | C1: tx Consumer-free | D1: tx Consumer-billable | E1: tx Business | F1: tx ROSCA | G1: ROSCA users | H1: Rev Consumer | I1: Rev Business | J1: Rev ROSCA | K1: TOTAL REVENUE | L1: Yapily | M1: Other opex | N1: Contingency 10% | O1: One-time | P1: TOTAL COST | Q1: EBT | R1: CUM CASH | S1: Gross margin %
A2: 1 | B2: 3233 | C2: 1293 | D2: 97 | E2: 1455 | F2: 388 | G2: =F2/Assumptions!$B$9 | H2: =D2*Assumptions!$B$5 | I2: =E2*Assumptions!$B$7 | J2: =G2*Assumptions!$B$8 | K2: =H2+I2+J2 | L2: =1100+Assumptions!$B$4*MAX(0,B2-Assumptions!$B$2) | M2: 3200 | N2: =0.1*(L2+M2) | O2: 4200 | P2: =L2+M2+N2+O2 | Q2: =K2-P2 | R2: =Q2 | S2: =IF(K2=0,0,(K2-L2)/K2)
A3: 2 | B3: 3773 | C3: 1509 | D3: 113 | E3: 1698 | F3: 453 | G3: =F3/Assumptions!$B$9 | H3: =D3*Assumptions!$B$5 | I3: =E3*Assumptions!$B$7 | J3: =G3*Assumptions!$B$8 | K3: =H3+I3+J3 | L3: =1100+Assumptions!$B$4*MAX(0,B3-Assumptions!$B$2) | M3: 3200 | N3: =0.1*(L3+M3) | O3: 0 | P3: =L3+M3+N3+O3 | Q3: =K3-P3 | R3: =R2+Q3 | S3: =IF(K3=0,0,(K3-L3)/K3)
A4: 3 | B4: 4397 | C4: 1759 | D4: 132 | E4: 1979 | F4: 528 | G4: =F4/Assumptions!$B$9 | H4: =D4*Assumptions!$B$5 | I4: =E4*Assumptions!$B$7 | J4: =G4*Assumptions!$B$8 | K4: =H4+I4+J4 | L4: =1100+Assumptions!$B$4*MAX(0,B4-Assumptions!$B$2) | M4: 3200 | N4: =0.1*(L4+M4) | O4: 0 | P4: =L4+M4+N4+O4 | Q4: =K4-P4 | R4: =R3+Q4 | S4: =IF(K4=0,0,(K4-L4)/K4)
A5: 4 | B5: 5120 | C5: 2048 | D5: 154 | E5: 2304 | F5: 614 | G5: =F5/Assumptions!$B$9 | H5: =D5*Assumptions!$B$5 | I5: =E5*Assumptions!$B$7 | J5: =G5*Assumptions!$B$8 | K5: =H5+I5+J5 | L5: =1100+Assumptions!$B$4*MAX(0,B5-Assumptions!$B$2) | M5: 6200 | N5: =0.1*(L5+M5) | O5: 0 | P5: =L5+M5+N5+O5 | Q5: =K5-P5 | R5: =R4+Q5 | S5: =IF(K5=0,0,(K5-L5)/K5)
A6: 5 | B6: 5953 | C6: 2381 | D6: 179 | E6: 2679 | F6: 714 | G6: =F6/Assumptions!$B$9 | H6: =D6*Assumptions!$B$5 | I6: =E6*Assumptions!$B$7 | J6: =G6*Assumptions!$B$8 | K6: =H6+I6+J6 | L6: =1100+Assumptions!$B$4*MAX(0,B6-Assumptions!$B$2) | M6: 6200 | N6: =0.1*(L6+M6) | O6: 0 | P6: =L6+M6+N6+O6 | Q6: =K6-P6 | R6: =R5+Q6 | S6: =IF(K6=0,0,(K6-L6)/K6)
A7: 6 | B7: 6912 | C7: 2765 | D7: 207 | E7: 3110 | F7: 829 | G7: =F7/Assumptions!$B$9 | H7: =D7*Assumptions!$B$5 | I7: =E7*Assumptions!$B$7 | J7: =G7*Assumptions!$B$8 | K7: =H7+I7+J7 | L7: =1100+Assumptions!$B$4*MAX(0,B7-Assumptions!$B$2) | M7: 6200 | N7: =0.1*(L7+M7) | O7: 0 | P7: =L7+M7+N7+O7 | Q7: =K7-P7 | R7: =R6+Q7 | S7: =IF(K7=0,0,(K7-L7)/K7)
A8: 7 | B8: 8011 | C8: 3205 | D8: 240 | E8: 3605 | F8: 961 | G8: =F8/Assumptions!$B$9 | H8: =D8*Assumptions!$B$5 | I8: =E8*Assumptions!$B$7 | J8: =G8*Assumptions!$B$8 | K8: =H8+I8+J8 | L8: =1100+Assumptions!$B$4*MAX(0,B8-Assumptions!$B$2) | M8: 13000 | N8: =0.1*(L8+M8) | O8: 1000 | P8: =L8+M8+N8+O8 | Q8: =K8-P8 | R8: =R7+Q8 | S8: =IF(K8=0,0,(K8-L8)/K8)
A9: 8 | B9: 9268 | C9: 3707 | D9: 278 | E9: 4170 | F9: 1112 | G9: =F9/Assumptions!$B$9 | H9: =D9*Assumptions!$B$5 | I9: =E9*Assumptions!$B$7 | J9: =G9*Assumptions!$B$8 | K9: =H9+I9+J9 | L9: =1100+Assumptions!$B$4*MAX(0,B9-Assumptions!$B$2) | M9: 13000 | N9: =0.1*(L9+M9) | O9: 0 | P9: =L9+M9+N9+O9 | Q9: =K9-P9 | R9: =R8+Q9 | S9: =IF(K9=0,0,(K9-L9)/K9)
A10: 9 | B10: 10697 | C10: 4279 | D10: 321 | E10: 4814 | F10: 1284 | G10: =F10/Assumptions!$B$9 | H10: =D10*Assumptions!$B$5 | I10: =E10*Assumptions!$B$7 | J10: =G10*Assumptions!$B$8 | K10: =H10+I10+J10 | L10: =1100+Assumptions!$B$4*MAX(0,B10-Assumptions!$B$2) | M10: 13000 | N10: =0.1*(L10+M10) | O10: 3000 | P10: =L10+M10+N10+O10 | Q10: =K10-P10 | R10: =R9+Q10 | S10: =IF(K10=0,0,(K10-L10)/K10)
A11: 10 | B11: 12316 | C11: 4926 | D11: 369 | E11: 5542 | F11: 1478 | G11: =F11/Assumptions!$B$9 | H11: =D11*Assumptions!$B$5 | I11: =E11*Assumptions!$B$7 | J11: =G11*Assumptions!$B$8 | K11: =H11+I11+J11 | L11: =1100+Assumptions!$B$4*MAX(0,B11-Assumptions!$B$2) | M11: 13000 | N11: =0.1*(L11+M11) | O11: 0 | P11: =L11+M11+N11+O11 | Q11: =K11-P11 | R11: =R10+Q11 | S11: =IF(K11=0,0,(K11-L11)/K11)
A12: 11 | B12: 14139 | C12: 5656 | D12: 424 | E12: 6363 | F12: 1697 | G12: =F12/Assumptions!$B$9 | H12: =D12*Assumptions!$B$5 | I12: =E12*Assumptions!$B$7 | J12: =G12*Assumptions!$B$8 | K12: =H12+I12+J12 | L12: =1100+Assumptions!$B$4*MAX(0,B12-Assumptions!$B$2) | M12: 13000 | N12: =0.1*(L12+M12) | O12: 0 | P12: =L12+M12+N12+O12 | Q12: =K12-P12 | R12: =R11+Q12 | S12: =IF(K12=0,0,(K12-L12)/K12)
A13: 12 | B13: 16180 | C13: 6472 | D13: 485 | E13: 7281 | F13: 1942 | G13: =F13/Assumptions!$B$9 | H13: =D13*Assumptions!$B$5 | I13: =E13*Assumptions!$B$7 | J13: =G13*Assumptions!$B$8 | K13: =H13+I13+J13 | L13: =1100+Assumptions!$B$4*MAX(0,B13-Assumptions!$B$2) | M13: 13000 | N13: =0.1*(L13+M13) | O13: 0 | P13: =L13+M13+N13+O13 | Q13: =K13-P13 | R13: =R12+Q13 | S13: =IF(K13=0,0,(K13-L13)/K13)
A14: 13 | B14: 8571 | C14: 3428 | D14: 300 | E14: 3686 | F14: 1157 | G14: =F14/Assumptions!$B$9 | H14: =D14*Assumptions!$B$5 | I14: =E14*Assumptions!$B$7 | J14: =G14*Assumptions!$B$8 | K14: =H14+I14+J14 | L14: =1100+Assumptions!$B$4*MAX(0,B14-Assumptions!$B$2) | M14: 25350 | N14: =0.1*(L14+M14) | O14: 0 | P14: =L14+M14+N14+O14 | Q14: =K14-P14 | R14: =R13+Q14 | S14: =IF(K14=0,0,(K14-L14)/K14)
... A18: 17 | B18: 13873 | C18: 5549 | D18: 486 | E18: 5965 | F18: 1873 | G18: =F18/Assumptions!$B$9 | H18: =D18*Assumptions!$B$5 | I18: =E18*Assumptions!$B$7 | J18: =G18*Assumptions!$B$8 | K18: =H18+I18+J18 | L18: =1100+Assumptions!$B$4*MAX(0,B18-Assumptions!$B$2) | M18: 25350 | N18: =0.1*(L18+M18) | O18: 0 | P18: =L18+M18+N18+O18 | Q18: =K18-P18 | R18: =R17+Q18 | S18: =IF(K18=0,0,(K18-L18)/K18)
A19: 18 | B19: 15449 | C19: 6180 | D19: 541 | E19: 6643 | F19: 2086 | G19: =F19/Assumptions!$B$9 | H19: =D19*Assumptions!$B$5 | I19: =E19*Assumptions!$B$7 | J19: =G19*Assumptions!$B$8 | K19: =H19+I19+J19 | L19: =1100+Assumptions!$B$4*MAX(0,(B19-F19)-Assumptions!$B$2)+Assumptions!$B$10*F19 | M19: 25350 | N19: =0.1*(L19+M19) | O19: 0 | P19: =L19+M19+N19+O19 | Q19: =K19-P19 | R19: =R18+Q19 | S19: =IF(K19=0,0,(K19-L19)/K19)
A20: 19 | B20: 17105 | C20: 6842 | D20: 599 | E20: 7355 | F20: 2309 | G20: =F20/Assumptions!$B$9 | H20: =D20*Assumptions!$B$5 | I20: =E20*Assumptions!$B$7 | J20: =G20*Assumptions!$B$8 | K20: =H20+I20+J20 | L20: =1100+Assumptions!$B$4*MAX(0,(B20-F20)-Assumptions!$B$2)+Assumptions!$B$10*F20 | M20: 29750 | N20: =0.1*(L20+M20) | O20: 0 | P20: =L20+M20+N20+O20 | Q20: =K20-P20 | R20: =R19+Q20 | S20: =IF(K20=0,0,(K20-L20)/K20)
A21: 20 | B21: 18824 | C21: 7530 | D21: 659 | E21: 8094 | F21: 2541 | G21: =F21/Assumptions!$B$9 | H21: =D21*Assumptions!$B$5 | I21: =E21*Assumptions!$B$7 | J21: =G21*Assumptions!$B$8 | K21: =H21+I21+J21 | L21: =1100+Assumptions!$B$4*MAX(0,(B21-F21)-Assumptions!$B$2)+Assumptions!$B$10*F21 | M21: 29750 | N21: =0.1*(L21+M21) | O21: 0 | P21: =L21+M21+N21+O21 | Q21: =K21-P21 | R21: =R20+Q21 | S21: =IF(K21=0,0,(K21-L21)/K21)
A22: 21 | B22: 20588 | C22: 8235 | D22: 721 | E22: 8853 | F22: 2779 | G22: =F22/Assumptions!$B$9 | H22: =D22*Assumptions!$B$5 | I22: =E22*Assumptions!$B$7 | J22: =G22*Assumptions!$B$8 | K22: =H22+I22+J22 | L22: =1100+Assumptions!$B$4*MAX(0,(B22-F22)-Assumptions!$B$2)+Assumptions!$B$10*F22 | M22: 29750 | N22: =0.1*(L22+M22) | O22: 0 | P22: =L22+M22+N22+O22 | Q22: =K22-P22 | R22: =R21+Q22 | S22: =IF(K22=0,0,(K22-L22)/K22)
A23: 22 | B23: 22374 | C23: 8950 | D23: 783 | E23: 9621 | F23: 3020 | G23: =F23/Assumptions!$B$9 | H23: =D23*Assumptions!$B$5 | I23: =E23*Assumptions!$B$7 | J23: =G23*Assumptions!$B$8 | K23: =H23+I23+J23 | L23: =1100+Assumptions!$B$4*MAX(0,(B23-F23)-Assumptions!$B$2)+Assumptions!$B$10*F23 | M23: 29750 | N23: =0.1*(L23+M23) | O23: 0 | P23: =L23+M23+N23+O23 | Q23: =K23-P23 | R23: =R22+Q23 | S23: =IF(K23=0,0,(K23-L23)/K23)
A24: 23 | B24: 24160 | C24: 9664 | D24: 846 | E24: 10389 | F24: 3262 | G24: =F24/Assumptions!$B$9 | H24: =D24*Assumptions!$B$5 | I24: =E24*Assumptions!$B$7 | J24: =G24*Assumptions!$B$8 | K24: =H24+I24+J24 | L24: =1100+Assumptions!$B$4*MAX(0,(B24-F24)-Assumptions!$B$2)+Assumptions!$B$10*F24 | M24: 29750 | N24: =0.1*(L24+M24) | O24: 0 | P24: =L24+M24+N24+O24 | Q24: =K24-P24 | R24: =R23+Q24 | S24: =IF(K24=0,0,(K24-L24)/K24)
A25: 24 | B25: 25923 | C25: 10369 | D25: 907 | E25: 11147 | F25: 3500 | G25: =F25/Assumptions!$B$9 | H25: =D25*Assumptions!$B$5 | I25: =E25*Assumptions!$B$7 | J25: =G25*Assumptions!$B$8 | K25: =H25+I25+J25 | L25: =1100+Assumptions!$B$4*MAX(0,(B25-F25)-Assumptions!$B$2)+Assumptions!$B$10*F25 | M25: 29750 | N25: =0.1*(L25+M25) | O25: 0 | P25: =L25+M25+N25+O25 | Q25: =K25-P25 | R25: =R24+Q25 | S25: =IF(K25=0,0,(K25-L25)/K25)
A26: 25 | B26: 23049 | C26: 9220 | D26: 922 | E26: 9681 | F26: 3227 | G26: =F26/Assumptions!$B$9 | H26: =D26*Assumptions!$B$5 | I26: =E26*Assumptions!$B$7 | J26: =G26*Assumptions!$B$8 | K26: =H26+I26+J26 | L26: =1100+Assumptions!$B$4*MAX(0,(B26-F26)-Assumptions!$B$2)+Assumptions!$B$10*F26 | M26: 39250 | N26: =0.1*(L26+M26) | O26: 0 | P26: =L26+M26+N26+O26 | Q26: =K26-P26 | R26: =R25+Q26 | S26: =IF(K26=0,0,(K26-L26)/K26)
A27: 26 | B27: 24430 | C27: 9772 | D27: 977 | E27: 10260 | F27: 3420 | G27: =F27/Assumptions!$B$9 | H27: =D27*Assumptions!$B$5 | I27: =E27*Assumptions!$B$7 | J27: =G27*Assumptions!$B$8 | K27: =H27+I27+J27 | L27: =1100+Assumptions!$B$4*MAX(0,(B27-F27)-Assumptions!$B$2)+Assumptions!$B$10*F27 | M27: 39250 | N27: =0.1*(L27+M27) | O27: 0 | P27: =L27+M27+N27+O27 | Q27: =K27-P27 | R27: =R26+Q27 | S27: =IF(K27=0,0,(K27-L27)/K27)
A28: 27 | B28: 25744 | C28: 10297 | D28: 1030 | E28: 10812 | F28: 3604 | G28: =F28/Assumptions!$B$9 | H28: =D28*Assumptions!$B$5 | I28: =E28*Assumptions!$B$7 | J28: =G28*Assumptions!$B$8 | K28: =H28+I28+J28 | L28: =1100+Assumptions!$B$4*MAX(0,(B28-F28)-Assumptions!$B$2)+Assumptions!$B$10*F28 | M28: 39250 | N28: =0.1*(L28+M28) | O28: 0 | P28: =L28+M28+N28+O28 | Q28: =K28-P28 | R28: =R27+Q28 | S28: =IF(K28=0,0,(K28-L28)/K28)
A29: 28 | B29: 26980 | C29: 10792 | D29: 1079 | E29: 11332 | F29: 3777 | G29: =F29/Assumptions!$B$9 | H29: =D29*Assumptions!$B$5 | I29: =E29*Assumptions!$B$7 | J29: =G29*Assumptions!$B$8 | K29: =H29+I29+J29 | L29: =1100+Assumptions!$B$4*MAX(0,(B29-F29)-Assumptions!$B$2)+Assumptions!$B$10*F29 | M29: 39250 | N29: =0.1*(L29+M29) | O29: 0 | P29: =L29+M29+N29+O29 | Q29: =K29-P29 | R29: =R28+Q29 | S29: =IF(K29=0,0,(K29-L29)/K29)
A30: 29 | B30: 28132 | C30: 11253 | D30: 1125 | E30: 11816 | F30: 3939 | G30: =F30/Assumptions!$B$9 | H30: =D30*Assumptions!$B$5 | I30: =E30*Assumptions!$B$7 | J30: =G30*Assumptions!$B$8 | K30: =H30+I30+J30 | L30: =1100+Assumptions!$B$4*MAX(0,(B30-F30)-Assumptions!$B$2)+Assumptions!$B$10*F30 | M30: 39250 | N30: =0.1*(L30+M30) | O30: 0 | P30: =L30+M30+N30+O30 | Q30: =K30-P30 | R30: =R29+Q30 | S30: =IF(K30=0,0,(K30-L30)/K30)
... A37: 36 | B37: 33721 | C37: 13488 | D37: 1349 | E37: 14163 | F37: 4721 | G37: =F37/Assumptions!$B$9 | H37: =D37*Assumptions!$B$5 | I37: =E37*Assumptions!$B$7 | J37: =G37*Assumptions!$B$8 | K37: =H37+I37+J37 | L37: =1100+Assumptions!$B$4*MAX(0,(B37-F37)-Assumptions!$B$2)+Assumptions!$B$10*F37 | M37: 39250 | N37: =0.1*(L37+M37) | O37: 0 | P37: =L37+M37+N37+O37 | Q37: =K37-P37 | R37: =R36+Q37 | S37: =IF(K37=0,0,(K37-L37)/K37)

Sheet Comparison
A1: Metric (3-year) | B1: Config A (EUR0.30 rail) | C1: Config B (viable)
A2: Transactions | B2: 650000 | C2: 650000
A3: Revenue | B3: 167163 | C3: 236343
A4: Yapily cost | B4: 202200 | C4: 88320
A5: Gross profit (rev - Yapily) | B5: -35037 | C5: 148023
A6: Net (EBT) | B6: -1062037 | C6: -867589
A7: Peak cash need | B7: -1062037 | C7: -867589
