Workbook

Sheet README
A1: PAYSPIN — 36-MONTH FINANCIAL MODEL
A3: Non-custodial SEPA-Instant payment-link + ROSCA fintech (NL/DE). PISP rail: Yapily (IbanXS backup).
A5: HOW TO USE THIS MODEL
A6: • 'Assumptions' sheet (yellow cells) holds the key levers: prices, ARPA, Yapily rates, tax.
A7: • 'Model' sheet = BASE CASE, monthly. Volume columns (blue) are inputs; money columns are LIVE FORMULAS.
A8: • Change a price/take-rate/tax cell on Assumptions and the whole Model + Annual sheets recompute.
A9: • 'Scenarios' compares Base / Best / Worst. 'Unit_Economics' holds LTV:CAC per segment.
A11: HEADLINE VERDICT (base case, conservative)
A12: • Consumer payment links barely monetise (P2P is free at Tikkie/banks) — treat as a viral funnel, not a revenue line.
A13: • The business payment-link stream is the only near-term profit engine; ROSCA is the sticky, differentiated wedge.
A14: • Monthly break-even is NOT reached within 36 months in Base/Worst; the Best case reaches it just past M36.
A15: • Peak cumulative funding need (base): ~€0.55M within 36m; ~€0.8–0.9M to actually reach break-even (~M42–46).
... A18: All figures EUR, exclusive of VAT. Built bottom-up; see build_payspin_model.py for derivation.

Sheet Assumptions
A1: ASSUMPTION | B1: VALUE | C1: NOTE / SOURCE
A2: c_price | B2: 0.5 | C2: EUR per billable consumer link (>3 free/mo). Tikkie consumer = free; WTP near zero.
A3: b_arpa | B3: 11 | C3: Blended monthly revenue per business account (subscription + per-tx). Tikkie biz €7.50+€0.15-0.25/tx.
A4: r_price_user_mo | B4: 1 | C4: ROSCA fee/user/mo. Comps: Roond 1.5% pot or €5.99/mo; StepLadder £1-18/mo.
A5: y_license | B5: 500 | C5: Yapily PISP licence rental (fixed).
A6: y_data | B6: 300 | C6: Yapily data usage (fixed).
A7: y_platform_base | B7: 300 | C7: Yapily platform fee base (incl. first 500 successful tx/mo).
A8: y_bundle_tx | B8: 500 | C8: Tx included in platform base.
A9: y_rate_t1 | B9: 0.2 | C9: ASSUMPTION: overage tx 501-5,000 (Yapily does not publish; <1% market).
A10: y_rate_t2 | B10: 0.12 | C10: ASSUMPTION: overage tx 5,001-25,000.
A11: y_rate_t3 | B11: 0.08 | C11: ASSUMPTION: overage tx 25,000+.
A12: tax_rate | B12: 0.22 | C12: Blended effective NL(19%)/DE UG(~30%) rate, applied AFTER loss carryforward.
A14: BEHAVIOURAL (baked into volume inputs on Model sheet)
A15: c_active_share | B15: 0.55 | C15: Active senders / registered.
A16: c_links_per_active | B16: 2.2 | C16: Links sent per active/mo.
A17: c_pay_rate | B17: 0.7 | C17: Sent links actually paid (=PISP tx).
A18: c_paid_conv | B18: 0.03 | C18: Active users exceeding free tier. Benchmark 2-5%.
A19: c_billable_per_payer | B19: 4 | C19: Billable links per paying user/mo.
A20: b_tx_per_acct | B20: 35 | C20: Completed tx per business acct/mo.
A21: r_users_per_circle | B21: 6 | C21: Avg ROSCA circle size.
A22: r_tx_per_circle | B22: 7 | C22: 6 contributions + 1 payout / mo.

Sheet Model
A1: Month | B1: Cons. registered | C1: Cons. active | D1: Cons. payers | E1: Cons. billable links | F1: Cons. tx | G1: Biz accounts | H1: Biz tx | I1: ROSCA circles | J1: ROSCA users | K1: ROSCA tx | L1: TOTAL tx | M1: Rev: Consumer | N1: Rev: Business | O1: Rev: ROSCA | P1: TOTAL REVENUE | Q1: Yapily | R1: Tech/dev | S1: Founder salary | T1: NL entity | U1: DE entity | V1: Legal/compliance | W1: Tools/infra | X1: PISP redundancy | Y1: Marketing | Z1: One-time | AA1: Contingency 10% | AB1: TOTAL COST | AC1: EBT | AD1: Loss c/f (open) | AE1: Taxable | AF1: Tax | AG1: Loss c/f (close) | AH1: NET PROFIT | AI1: CUM CASH | AJ1: Gross margin %
A2: 1 | B2: 134 | C2: 74 | D2: 2.2 | E2: 8.9 | F2: 114 | G2: 0 | H2: 0 | I2: 0 | J2: 0 | K2: 0 | L2: =F2+H2+K2 | M2: =E2*Assumptions!$B$2 | N2: =G2*Assumptions!$B$3 | O2: =J2*Assumptions!$B$4 | P2: =M2+N2+O2 | Q2: =Assumptions!$B$5+Assumptions!$B$6+Assumptions!$B$7+MIN(MAX(0,L2-Assumptions!$B$8),4500)*Assumptions!$B$9+MIN(MAX(MAX(0,L2-Assumptions!$B$8)-4500,0),20000)*Assumptions!$B$10+MAX(MAX(0,L2-Assumptions!$B$8)-24500,0)*Assumptions!$B$11 | R2: 300 | S2: 0 | T2: 450 | U2: 0 | V2: 150 | W2: 200 | X2: 0 | Y2: 800 | Z2: 4200 | AA2: =0.1*(Q2+R2+S2+T2+U2+V2+W2+X2+Y2) | AB2: =(Q2+R2+S2+T2+U2+V2+W2+X2+Y2)+Z2+AA2 | AC2: =P2-AB2 | AD2: 0 | AE2: =MAX(0,AC2-AD2) | AF2: =AE2*Assumptions!$B$12 | AG2: =MAX(0,AD2-MAX(AC2,0))+MAX(0,-AC2) | AH2: =AC2-AF2 | AI2: =AH2 | AJ2: =IF(P2=0,0,(P2-Q2)/P2)
A3: 2 | B3: 157 | C3: 87 | D3: 2.6 | E3: 10.4 | F3: 133 | G3: 0 | H3: 0 | I3: 0 | J3: 0 | K3: 0 | L3: =F3+H3+K3 | M3: =E3*Assumptions!$B$2 | N3: =G3*Assumptions!$B$3 | O3: =J3*Assumptions!$B$4 | P3: =M3+N3+O3 | Q3: =Assumptions!$B$5+Assumptions!$B$6+Assumptions!$B$7+MIN(MAX(0,L3-Assumptions!$B$8),4500)*Assumptions!$B$9+MIN(MAX(MAX(0,L3-Assumptions!$B$8)-4500,0),20000)*Assumptions!$B$10+MAX(MAX(0,L3-Assumptions!$B$8)-24500,0)*Assumptions!$B$11 | R3: 300 | S3: 0 | T3: 450 | U3: 0 | V3: 150 | W3: 200 | X3: 0 | Y3: 800 | Z3: 0 | AA3: =0.1*(Q3+R3+S3+T3+U3+V3+W3+X3+Y3) | AB3: =(Q3+R3+S3+T3+U3+V3+W3+X3+Y3)+Z3+AA3 | AC3: =P3-AB3 | AD3: =AG2 | AE3: =MAX(0,AC3-AD3) | AF3: =AE3*Assumptions!$B$12 | AG3: =MAX(0,AD3-MAX(AC3,0))+MAX(0,-AC3) | AH3: =AC3-AF3 | AI3: =AI2+AH3 | AJ3: =IF(P3=0,0,(P3-Q3)/P3)
A4: 3 | B4: 186 | C4: 102 | D4: 3.1 | E4: 12.3 | F4: 158 | G4: 0 | H4: 0 | I4: 0 | J4: 0 | K4: 0 | L4: =F4+H4+K4 | M4: =E4*Assumptions!$B$2 | N4: =G4*Assumptions!$B$3 | O4: =J4*Assumptions!$B$4 | P4: =M4+N4+O4 | Q4: =Assumptions!$B$5+Assumptions!$B$6+Assumptions!$B$7+MIN(MAX(0,L4-Assumptions!$B$8),4500)*Assumptions!$B$9+MIN(MAX(MAX(0,L4-Assumptions!$B$8)-4500,0),20000)*Assumptions!$B$10+MAX(MAX(0,L4-Assumptions!$B$8)-24500,0)*Assumptions!$B$11 | R4: 300 | S4: 0 | T4: 450 | U4: 0 | V4: 150 | W4: 200 | X4: 0 | Y4: 800 | Z4: 0 | AA4: =0.1*(Q4+R4+S4+T4+U4+V4+W4+X4+Y4) | AB4: =(Q4+R4+S4+T4+U4+V4+W4+X4+Y4)+Z4+AA4 | AC4: =P4-AB4 | AD4: =AG3 | AE4: =MAX(0,AC4-AD4) | AF4: =AE4*Assumptions!$B$12 | AG4: =MAX(0,AD4-MAX(AC4,0))+MAX(0,-AC4) | AH4: =AC4-AF4 | AI4: =AI3+AH4 | AJ4: =IF(P4=0,0,(P4-Q4)/P4)
A5: 4 | B5: 221 | C5: 122 | D5: 3.7 | E5: 14.6 | F5: 188 | G5: 4 | H5: 149 | I5: 0 | J5: 0 | K5: 0 | L5: =F5+H5+K5 | M5: =E5*Assumptions!$B$2 | N5: =G5*Assumptions!$B$3 | O5: =J5*Assumptions!$B$4 | P5: =M5+N5+O5 | Q5: =Assumptions!$B$5+Assumptions!$B$6+Assumptions!$B$7+MIN(MAX(0,L5-Assumptions!$B$8),4500)*Assumptions!$B$9+MIN(MAX(MAX(0,L5-Assumptions!$B$8)-4500,0),20000)*Assumptions!$B$10+MAX(MAX(0,L5-Assumptions!$B$8)-24500,0)*Assumptions!$B$11 | R5: 300 | S5: 0 | T5: 450 | U5: 0 | V5: 150 | W5: 200 | X5: 0 | Y5: 1500 | Z5: 0 | AA5: =0.1*(Q5+R5+S5+T5+U5+V5+W5+X5+Y5) | AB5: =(Q5+R5+S5+T5+U5+V5+W5+X5+Y5)+Z5+AA5 | AC5: =P5-AB5 | AD5: =AG4 | AE5: =MAX(0,AC5-AD5) | AF5: =AE5*Assumptions!$B$12 | AG5: =MAX(0,AD5-MAX(AC5,0))+MAX(0,-AC5) | AH5: =AC5-AF5 | AI5: =AI4+AH5 | AJ5: =IF(P5=0,0,(P5-Q5)/P5)
A6: 5 | B6: 265 | C6: 146 | D6: 4.4 | E6: 17.5 | F6: 225 | G6: 5 | H6: 173 | I6: 0 | J6: 0 | K6: 0 | L6: =F6+H6+K6 | M6: =E6*Assumptions!$B$2 | N6: =G6*Assumptions!$B$3 | O6: =J6*Assumptions!$B$4 | P6: =M6+N6+O6 | Q6: =Assumptions!$B$5+Assumptions!$B$6+Assumptions!$B$7+MIN(MAX(0,L6-Assumptions!$B$8),4500)*Assumptions!$B$9+MIN(MAX(MAX(0,L6-Assumptions!$B$8)-4500,0),20000)*Assumptions!$B$10+MAX(MAX(0,L6-Assumptions!$B$8)-24500,0)*Assumptions!$B$11 | R6: 300 | S6: 0 | T6: 450 | U6: 0 | V6: 150 | W6: 200 | X6: 0 | Y6: 1500 | Z6: 0 | AA6: =0.1*(Q6+R6+S6+T6+U6+V6+W6+X6+Y6) | AB6: =(Q6+R6+S6+T6+U6+V6+W6+X6+Y6)+Z6+AA6 | AC6: =P6-AB6 | AD6: =AG5 | AE6: =MAX(0,AC6-AD6) | AF6: =AE6*Assumptions!$B$12 | AG6: =MAX(0,AD6-MAX(AC6,0))+MAX(0,-AC6) | AH6: =AC6-AF6 | AI6: =AI5+AH6 | AJ6: =IF(P6=0,0,(P6-Q6)/P6)
A7: 6 | B7: 320 | C7: 176 | D7: 5.3 | E7: 21.1 | F7: 271 | G7: 6 | H7: 203 | I7: 5 | J7: 31 | K7: 36 | L7: =F7+H7+K7 | M7: =E7*Assumptions!$B$2 | N7: =G7*Assumptions!$B$3 | O7: =J7*Assumptions!$B$4 | P7: =M7+N7+O7 | Q7: =Assumptions!$B$5+Assumptions!$B$6+Assumptions!$B$7+MIN(MAX(0,L7-Assumptions!$B$8),4500)*Assumptions!$B$9+MIN(MAX(MAX(0,L7-Assumptions!$B$8)-4500,0),20000)*Assumptions!$B$10+MAX(MAX(0,L7-Assumptions!$B$8)-24500,0)*Assumptions!$B$11 | R7: 300 | S7: 0 | T7: 450 | U7: 0 | V7: 150 | W7: 200 | X7: 0 | Y7: 1500 | Z7: 0 | AA7: =0.1*(Q7+R7+S7+T7+U7+V7+W7+X7+Y7) | AB7: =(Q7+R7+S7+T7+U7+V7+W7+X7+Y7)+Z7+AA7 | AC7: =P7-AB7 | AD7: =AG6 | AE7: =MAX(0,AC7-AD7) | AF7: =AE7*Assumptions!$B$12 | AG7: =MAX(0,AD7-MAX(AC7,0))+MAX(0,-AC7) | AH7: =AC7-AF7 | AI7: =AI6+AH7 | AJ7: =IF(P7=0,0,(P7-Q7)/P7)
A8: 7 | B8: 387 | C8: 213 | D8: 6.4 | E8: 25.5 | F8: 328 | G8: 7 | H8: 242 | I8: 6 | J8: 38 | K8: 44 | L8: =F8+H8+K8 | M8: =E8*Assumptions!$B$2 | N8: =G8*Assumptions!$B$3 | O8: =J8*Assumptions!$B$4 | P8: =M8+N8+O8 | Q8: =Assumptions!$B$5+Assumptions!$B$6+Assumptions!$B$7+MIN(MAX(0,L8-Assumptions!$B$8),4500)*Assumptions!$B$9+MIN(MAX(MAX(0,L8-Assumptions!$B$8)-4500,0),20000)*Assumptions!$B$10+MAX(MAX(0,L8-Assumptions!$B$8)-24500,0)*Assumptions!$B$11 | R8: 1500 | S8: 0 | T8: 450 | U8: 300 | V8: 150 | W8: 400 | X8: 0 | Y8: 3000 | Z8: 1000 | AA8: =0.1*(Q8+R8+S8+T8+U8+V8+W8+X8+Y8) | AB8: =(Q8+R8+S8+T8+U8+V8+W8+X8+Y8)+Z8+AA8 | AC8: =P8-AB8 | AD8: =AG7 | AE8: =MAX(0,AC8-AD8) | AF8: =AE8*Assumptions!$B$12 | AG8: =MAX(0,AD8-MAX(AC8,0))+MAX(0,-AC8) | AH8: =AC8-AF8 | AI8: =AI7+AH8 | AJ8: =IF(P8=0,0,(P8-Q8)/P8)
A9: 8 | B9: 470 | C9: 259 | D9: 7.8 | E9: 31 | F9: 398 | G9: 8 | H9: 293 | I9: 8 | J9: 46 | K9: 54 | L9: =F9+H9+K9 | M9: =E9*Assumptions!$B$2 | N9: =G9*Assumptions!$B$3 | O9: =J9*Assumptions!$B$4 | P9: =M9+N9+O9 | Q9: =Assumptions!$B$5+Assumptions!$B$6+Assumptions!$B$7+MIN(MAX(0,L9-Assumptions!$B$8),4500)*Assumptions!$B$9+MIN(MAX(MAX(0,L9-Assumptions!$B$8)-4500,0),20000)*Assumptions!$B$10+MAX(MAX(0,L9-Assumptions!$B$8)-24500,0)*Assumptions!$B$11 | R9: 1500 | S9: 0 | T9: 450 | U9: 300 | V9: 150 | W9: 400 | X9: 0 | Y9: 3000 | Z9: 0 | AA9: =0.1*(Q9+R9+S9+T9+U9+V9+W9+X9+Y9) | AB9: =(Q9+R9+S9+T9+U9+V9+W9+X9+Y9)+Z9+AA9 | AC9: =P9-AB9 | AD9: =AG8 | AE9: =MAX(0,AC9-AD9) | AF9: =AE9*Assumptions!$B$12 | AG9: =MAX(0,AD9-MAX(AC9,0))+MAX(0,-AC9) | AH9: =AC9-AF9 | AI9: =AI8+AH9 | AJ9: =IF(P9=0,0,(P9-Q9)/P9)
A10: 9 | B10: 572 | C10: 315 | D10: 9.4 | E10: 37.8 | F10: 485 | G10: 10 | H10: 359 | I10: 10 | J10: 57 | K10: 67 | L10: =F10+H10+K10 | M10: =E10*Assumptions!$B$2 | N10: =G10*Assumptions!$B$3 | O10: =J10*Assumptions!$B$4 | P10: =M10+N10+O10 | Q10: =Assumptions!$B$5+Assumptions!$B$6+Assumptions!$B$7+MIN(MAX(0,L10-Assumptions!$B$8),4500)*Assumptions!$B$9+MIN(MAX(MAX(0,L10-Assumptions!$B$8)-4500,0),20000)*Assumptions!$B$10+MAX(MAX(0,L10-Assumptions!$B$8)-24500,0)*Assumptions!$B$11 | R10: 1500 | S10: 0 | T10: 450 | U10: 300 | V10: 150 | W10: 400 | X10: 0 | Y10: 3000 | Z10: 3000 | AA10: =0.1*(Q10+R10+S10+T10+U10+V10+W10+X10+Y10) | AB10: =(Q10+R10+S10+T10+U10+V10+W10+X10+Y10)+Z10+AA10 | AC10: =P10-AB10 | AD10: =AG9 | AE10: =MAX(0,AC10-AD10) | AF10: =AE10*Assumptions!$B$12 | AG10: =MAX(0,AD10-MAX(AC10,0))+MAX(0,-AC10) | AH10: =AC10-AF10 | AI10: =AI9+AH10 | AJ10: =IF(P10=0,0,(P10-Q10)/P10)
A11: 10 | B11: 697 | C11: 384 | D11: 11.5 | E11: 46 | F11: 591 | G11: 13 | H11: 444 | I11: 12 | J11: 71 | K11: 83 | L11: =F11+H11+K11 | M11: =E11*Assumptions!$B$2 | N11: =G11*Assumptions!$B$3 | O11: =J11*Assumptions!$B$4 | P11: =M11+N11+O11 | Q11: =Assumptions!$B$5+Assumptions!$B$6+Assumptions!$B$7+MIN(MAX(0,L11-Assumptions!$B$8),4500)*Assumptions!$B$9+MIN(MAX(MAX(0,L11-Assumptions!$B$8)-4500,0),20000)*Assumptions!$B$10+MAX(MAX(0,L11-Assumptions!$B$8)-24500,0)*Assumptions!$B$11 | R11: 1500 | S11: 0 | T11: 450 | U11: 300 | V11: 150 | W11: 400 | X11: 0 | Y11: 3000 | Z11: 0 | AA11: =0.1*(Q11+R11+S11+T11+U11+V11+W11+X11+Y11) | AB11: =(Q11+R11+S11+T11+U11+V11+W11+X11+Y11)+Z11+AA11 | AC11: =P11-AB11 | AD11: =AG10 | AE11: =MAX(0,AC11-AD11) | AF11: =AE11*Assumptions!$B$12 | AG11: =MAX(0,AD11-MAX(AC11,0))+MAX(0,-AC11) | AH11: =AC11-AF11 | AI11: =AI10+AH11 | AJ11: =IF(P11=0,0,(P11-Q11)/P11)
A12: 11 | B12: 850 | C12: 468 | D12: 14 | E12: 56.1 | F12: 720 | G12: 16 | H12: 553 | I12: 15 | J12: 88 | K12: 103 | L12: =F12+H12+K12 | M12: =E12*Assumptions!$B$2 | N12: =G12*Assumptions!$B$3 | O12: =J12*Assumptions!$B$4 | P12: =M12+N12+O12 | Q12: =Assumptions!$B$5+Assumptions!$B$6+Assumptions!$B$7+MIN(MAX(0,L12-Assumptions!$B$8),4500)*Assumptions!$B$9+MIN(MAX(MAX(0,L12-Assumptions!$B$8)-4500,0),20000)*Assumptions!$B$10+MAX(MAX(0,L12-Assumptions!$B$8)-24500,0)*Assumptions!$B$11 | R12: 1500 | S12: 0 | T12: 450 | U12: 300 | V12: 150 | W12: 400 | X12: 0 | Y12: 3000 | Z12: 0 | AA12: =0.1*(Q12+R12+S12+T12+U12+V12+W12+X12+Y12) | AB12: =(Q12+R12+S12+T12+U12+V12+W12+X12+Y12)+Z12+AA12 | AC12: =P12-AB12 | AD12: =AG11 | AE12: =MAX(0,AC12-AD12) | AF12: =AE12*Assumptions!$B$12 | AG12: =MAX(0,AD12-MAX(AC12,0))+MAX(0,-AC12) | AH12: =AC12-AF12 | AI12: =AI11+AH12 | AJ12: =IF(P12=0,0,(P12-Q12)/P12)
A13: 12 | B13: 1036 | C13: 570 | D13: 17.1 | E13: 68.4 | F13: 878 | G13: 20 | H13: 694 | I13: 18 | J13: 110 | K13: 128 | L13: =F13+H13+K13 | M13: =E13*Assumptions!$B$2 | N13: =G13*Assumptions!$B$3 | O13: =J13*Assumptions!$B$4 | P13: =M13+N13+O13 | Q13: =Assumptions!$B$5+Assumptions!$B$6+Assumptions!$B$7+MIN(MAX(0,L13-Assumptions!$B$8),4500)*Assumptions!$B$9+MIN(MAX(MAX(0,L13-Assumptions!$B$8)-4500,0),20000)*Assumptions!$B$10+MAX(MAX(0,L13-Assumptions!$B$8)-24500,0)*Assumptions!$B$11 | R13: 1500 | S13: 0 | T13: 450 | U13: 300 | V13: 150 | W13: 400 | X13: 0 | Y13: 3000 | Z13: 0 | AA13: =0.1*(Q13+R13+S13+T13+U13+V13+W13+X13+Y13) | AB13: =(Q13+R13+S13+T13+U13+V13+W13+X13+Y13)+Z13+AA13 | AC13: =P13-AB13 | AD13: =AG12 | AE13: =MAX(0,AC13-AD13) | AF13: =AE13*Assumptions!$B$12 | AG13: =MAX(0,AD13-MAX(AC13,0))+MAX(0,-AC13) | AH13: =AC13-AF13 | AI13: =AI12+AH13 | AJ13: =IF(P13=0,0,(P13-Q13)/P13)
A14: 13 | B14: 1262 | C14: 694 | D14: 20.8 | E14: 83.3 | F14: 1069 | G14: 25 | H14: 874 | I14: 23 | J14: 137 | K14: 160 | L14: =F14+H14+K14 | M14: =E14*Assumptions!$B$2 | N14: =G14*Assumptions!$B$3 | O14: =J14*Assumptions!$B$4 | P14: =M14+N14+O14 | Q14: =Assumptions!$B$5+Assumptions!$B$6+Assumptions!$B$7+MIN(MAX(0,L14-Assumptions!$B$8),4500)*Assumptions!$B$9+MIN(MAX(MAX(0,L14-Assumptions!$B$8)-4500,0),20000)*Assumptions!$B$10+MAX(MAX(0,L14-Assumptions!$B$8)-24500,0)*Assumptions!$B$11 | R14: 4000 | S14: 1500 | T14: 450 | U14: 300 | V14: 150 | W14: 400 | X14: 350 | Y14: 6000 | Z14: 0 | AA14: =0.1*(Q14+R14+S14+T14+U14+V14+W14+X14+Y14) | AB14: =(Q14+R14+S14+T14+U14+V14+W14+X14+Y14)+Z14+AA14 | AC14: =P14-AB14 | AD14: =AG13 | AE14: =MAX(0,AC14-AD14) | AF14: =AE14*Assumptions!$B$12 | AG14: =MAX(0,AD14-MAX(AC14,0))+MAX(0,-AC14) | AH14: =AC14-AF14 | AI14: =AI13+AH14 | AJ14: =IF(P14=0,0,(P14-Q14)/P14)
... A37: 36 | B37: 14004 | C37: 7702 | D37: 231.1 | E37: 924.2 | F37: 11861 | G37: 821 | H37: 28738 | I37: 583 | J37: 3497 | K37: 4080 | L37: =F37+H37+K37 | M37: =E37*Assumptions!$B$2 | N37: =G37*Assumptions!$B$3 | O37: =J37*Assumptions!$B$4 | P37: =M37+N37+O37 | Q37: =Assumptions!$B$5+Assumptions!$B$6+Assumptions!$B$7+MIN(MAX(0,L37-Assumptions!$B$8),4500)*Assumptions!$B$9+MIN(MAX(MAX(0,L37-Assumptions!$B$8)-4500,0),20000)*Assumptions!$B$10+MAX(MAX(0,L37-Assumptions!$B$8)-24500,0)*Assumptions!$B$11 | R37: 9000 | S37: 3000 | T37: 450 | U37: 300 | V37: 150 | W37: 800 | X37: 350 | Y37: 10000 | Z37: 0 | AA37: =0.1*(Q37+R37+S37+T37+U37+V37+W37+X37+Y37) | AB37: =(Q37+R37+S37+T37+U37+V37+W37+X37+Y37)+Z37+AA37 | AC37: =P37-AB37 | AD37: =AG36 | AE37: =MAX(0,AC37-AD37) | AF37: =AE37*Assumptions!$B$12 | AG37: =MAX(0,AD37-MAX(AC37,0))+MAX(0,-AC37) | AH37: =AC37-AF37 | AI37: =AI36+AH37 | AJ37: =IF(P37=0,0,(P37-Q37)/P37)

Sheet Annual_Summary
B1: Year 1 (M1-12) | C1: Year 2 (M13-24) | D1: Year 3 (M25-36)
A2: Total revenue | B2: =SUM(Model!P2:P13) | C2: =SUM(Model!P14:P25) | D2: =SUM(Model!P26:P37)
A3: Total cost | B3: =SUM(Model!AB2:AB13) | C3: =SUM(Model!AB14:AB25) | D3: =SUM(Model!AB26:AB37)
A4: Net profit/(loss) | B4: =SUM(Model!AH2:AH13) | C4: =SUM(Model!AH14:AH25) | D4: =SUM(Model!AH26:AH37)
A5: Yapily cost | B5: =SUM(Model!Q2:Q13) | C5: =SUM(Model!Q14:Q25) | D5: =SUM(Model!Q26:Q37)
A6: Marketing | B6: =SUM(Model!Y2:Y13) | C6: =SUM(Model!Y14:Y25) | D6: =SUM(Model!Y26:Y37)
A7: Cum cash (year-end) | B7: =Model!AI13 | C7: =Model!AI25 | D7: =Model!AI37

Sheet Scenarios
A1: Scenario | B1: Y1 rev | C1: Y2 rev | D1: Y3 rev | E1: Exit M36 MRR | F1: M36 tx/mo | G1: Monthly break-even | H1: Peak funding need (36m)
A2: WORST | B2: 792 | C2: 11666 | D2: 57815 | E2: 6394 | F2: 24185 | G2: beyond M36 | H2: -623247
A3: BASE | B3: 1593 | C3: 23531 | D3: 117444 | E3: 12992 | F3: 44680 | G3: beyond M36 | H3: -552419
A4: BEST | B4: 3616 | C4: 54565 | D4: 278633 | E4: 30879 | F4: 86728 | G4: beyond M36 | H4: -380350
A6: Scenario levers
B7: consumer conv x | C7: biz accounts x | D7: biz ARPA € | E7: ROSCA vol x | F7: Yapily cost x
A8: WORST | B8: 0.5 | C8: 0.55 | D8: 9 | E8: 0.6 | F8: 1.3
A9: BASE | B9: 1 | C9: 1 | D9: 11 | E9: 1 | F9: 1
A10: BEST | B10: 1.5 | C10: 2.2 | D10: 14 | E10: 1.4 | F10: 0.85

Sheet Unit_Economics
A1: Segment | B1: ARPU/mo € | C1: Gross margin | D1: Avg life (mo) | E1: LTV € | F1: CAC € | G1: LTV:CAC | H1: Verdict
A2: Consumer (paying) | B2: 2 | C2: 0.6 | D2: 18 | E2: =B2*C2*D2 | F2: 6 | G2: =E2/F2 | H2: Marginal; only via organic/viral
A3: Consumer (blended all users) | B3: 0.1 | C3: 0.6 | D3: 14 | E3: =B3*C3*D3 | F3: 6 | G3: =E3/F3 | H3: Do NOT buy paid traffic
A4: Business account | B4: 11 | C4: 0.75 | D4: 30 | E4: =B4*C4*D4 | F4: 90 | G4: =E4/F4 | H4: Primary profit engine
A5: ROSCA user | B5: 1 | C5: 0.8 | D5: 12 | E5: =B5*C5*D5 | F5: 5 | G5: =E5/F5 | H5: Sticky, cheap (community-led)
A6: ROSCA (per 6-person circle) | B6: 6 | C6: 0.8 | D6: 12 | E6: =B6*C6*D6 | F6: 18 | G6: =E6/F6 | H6: Acquire 6 users per CAC event
